sqlalchemy_facets/__init__.py
sqlalchemy_facets/api.py
sqlalchemy_facets/facet.py
sqlalchemy_facets/formatter.py
sqlalchemy_facets/query.py
sqlalchemy_facets/utils.py
sqlalchemy_facets-0.1.4.dist-info/WHEEL
sqlalchemy_facets-0.1.4.dist-info/METADATA
sqlalchemy_facets-0.1.4.dist-info/RECORD
