Metadata-Version: 2.1
Name: sqlalchemy-facets
Version: 0.1.4
Summary: Faceted search for SQLAlchemy
Author: Thibaut Frain
Author-email: thibaut.frain@gmail.com
Requires-Python: >=3.6,<4
Classifier: Programming Language :: Python :: 3
Classifier: Programming Language :: Python :: 3.6
Classifier: Programming Language :: Python :: 3.7
Classifier: Programming Language :: Python :: 3.8
Classifier: Programming Language :: Python :: 3.9
Classifier: Programming Language :: Python :: 3.10
Classifier: Programming Language :: Python :: 3.11
Requires-Dist: sqlalchemy (>=1.3.13,<2.0.0)
